{
	"info": {
		"_postman_id": "14f1a8d5-c892-4b72-bbc7-58a55867f9d2",
		"name": "AI Enhance - New Backend",
		"schema": "https://schema.getpostman.com/json/collection/v2.1.0/collection.json",
		"_exporter_id": "34436152",
		"_collection_link": "https://ai-enhance-3385.postman.co/workspace/AI-Enhance-Workspace~dd57ab79-100d-48f9-b76c-833910c1b1b6/collection/37425431-14f1a8d5-c892-4b72-bbc7-58a55867f9d2?action=share&source=collection_link&creator=34436152"
	},
	"item": [
		{
			"name": "User",
			"item": [
				{
					"name": "Sign-up",
					"request": {
						"method": "POST",
						"header": [
							{
								"key": "Content-Type",
								"value": "application/json"
							}
						],
						"body": {
							"mode": "raw",
							"raw": "{\n    \"username\": \"example_user\",\n    \"email\": \"user@example.com\",\n    \"password\": \"password123\",\n    \"phone\": \"1234567890\",\n    \"user_type\": \"ORGANIZATION\",  # or \"AGENCY\" or \"CLIENT\"\n    \"entity_data\": {\n        # For ORGANIZATION:\n        \"name\": \"Organization Name\",\n        \"address\": \"Organization Address\"\n        \n        # For AGENCY:\n        \"name\": \"Agency Name\",\n        \"address\": \"Agency Address\",\n        \"organization_id\": \"org_id_here\"\n        \n        # For CLIENT:\n        \"business_name\": \"Client Business\",\n        \"agency_id\": \"agency_id_here\"\n    }\n}",
							"options": {
								"raw": {
									"language": "json"
								}
							}
						},
						"url": {
							"raw": "http://localhost:3000/api/users/signup",
							"protocol": "http",
							"host": [
								"localhost"
							],
							"port": "3000",
							"path": [
								"api",
								"users",
								"signup"
							]
						}
					},
					"response": []
				},
				{
					"name": "Login",
					"request": {
						"method": "POST",
						"header": [
							{
								"key": "Content-Type",
								"value": "application/json"
							}
						],
						"body": {
							"mode": "raw",
							"raw": "{\n    \"username\": \"example_user\",\n    \"password\": \"password123\"\n}",
							"options": {
								"raw": {
									"language": "json"
								}
							}
						},
						"url": {
							"raw": "http://localhost:3000/api/users/login",
							"protocol": "http",
							"host": [
								"localhost"
							],
							"port": "3000",
							"path": [
								"api",
								"users",
								"login"
							]
						}
					},
					"response": []
				},
				{
					"name": "Get User Details",
					"request": {
						"method": "GET",
						"header": [
							{
								"key": "Authorization",
								"value": "Bearer YOUR_ACCESS_TOKEN"
							}
						],
						"url": {
							"raw": "http://localhost:3000/api/users/:user_id",
							"protocol": "http",
							"host": [
								"localhost"
							],
							"port": "3000",
							"path": [
								"api",
								"users",
								":user_id"
							],
							"variable": [
								{
									"key": "user_id",
									"value": ""
								}
							]
						}
					},
					"response": []
				},
				{
					"name": "Update User",
					"request": {
						"method": "PATCH",
						"header": [
							{
								"key": "Authorization",
								"value": "Bearer YOUR_ACCESS_TOKEN"
							},
							{
								"key": "Content-Type",
								"value": "application/json"
							}
						],
						"body": {
							"mode": "raw",
							"raw": "{\n    \"username\": \"new_username\",\n    \"email\": \"new@email.com\",\n    \"phone\": \"9876543210\",\n    \"entity_data\": {\n        \"name\": \"Updated Name\",\n        \"address\": \"Updated Address\"\n    }\n}",
							"options": {
								"raw": {
									"language": "json"
								}
							}
						},
						"url": {
							"raw": "http://localhost:3000/api/users/:user_id",
							"protocol": "http",
							"host": [
								"localhost"
							],
							"port": "3000",
							"path": [
								"api",
								"users",
								":user_id"
							],
							"variable": [
								{
									"key": "user_id",
									"value": ""
								}
							]
						}
					},
					"response": []
				},
				{
					"name": "Delete User",
					"request": {
						"method": "DELETE",
						"header": [
							{
								"key": "Authorization",
								"value": "Bearer YOUR_ACCESS_TOKEN"
							}
						],
						"url": {
							"raw": "http://localhost:3000/api/users/:user_id",
							"protocol": "http",
							"host": [
								"localhost"
							],
							"port": "3000",
							"path": [
								"api",
								"users",
								":user_id"
							],
							"variable": [
								{
									"key": "user_id",
									"value": ""
								}
							]
						}
					},
					"response": []
				},
				{
					"name": "Refresh Token",
					"request": {
						"method": "POST",
						"header": [
							{
								"key": "Content-Type",
								"value": "application/json"
							}
						],
						"body": {
							"mode": "raw",
							"raw": "{\n    \"refreshToken\": \"YOUR_REFRESH_TOKEN\"\n}",
							"options": {
								"raw": {
									"language": "json"
								}
							}
						},
						"url": {
							"raw": "http://localhost:3000/api/users/refresh-token",
							"protocol": "http",
							"host": [
								"localhost"
							],
							"port": "3000",
							"path": [
								"api",
								"users",
								"refresh-token"
							]
						}
					},
					"response": []
				},
				{
					"name": "Check Token",
					"request": {
						"method": "GET",
						"header": []
					},
					"response": []
				}
			]
		},
		{
			"name": "Organizations",
			"item": [
				{
					"name": "Get ALL Organizations",
					"request": {
						"method": "GET",
						"header": [
							{
								"key": "Authorization",
								"value": "Bearer YOUR_ACCESS_TOKEN"
							}
						],
						"url": {
							"raw": "http://localhost:3000/api/organizations",
							"protocol": "http",
							"host": [
								"localhost"
							],
							"port": "3000",
							"path": [
								"api",
								"organizations"
							]
						}
					},
					"response": []
				},
				{
					"name": "Get an Organization",
					"request": {
						"method": "GET",
						"header": [
							{
								"key": "Authorization",
								"value": "Bearer YOUR_ACCESS_TOKEN"
							}
						],
						"url": {
							"raw": "http://localhost:3000/api/organizations/:organization_id",
							"protocol": "http",
							"host": [
								"localhost"
							],
							"port": "3000",
							"path": [
								"api",
								"organizations",
								":organization_id"
							],
							"variable": [
								{
									"key": "organization_id",
									"value": ""
								}
							]
						}
					},
					"response": []
				},
				{
					"name": "Create Organization",
					"request": {
						"method": "POST",
						"header": [
							{
								"key": "Authorization",
								"value": "Bearer YOUR_ACCESS_TOKEN"
							},
							{
								"key": "Content-Type",
								"value": "application/json"
							}
						],
						"body": {
							"mode": "raw",
							"raw": "{\n    \"name\": \"New Organization\",\n    \"email\": \"org@example.com\",\n    \"phone_number\": \"1234567890\",\n    \"address\": \"Organization Address\",\n    \"user_id\": \"USER_ID_HERE\"\n}",
							"options": {
								"raw": {
									"language": "json"
								}
							}
						},
						"url": {
							"raw": "http://localhost:3000/api/organizations",
							"protocol": "http",
							"host": [
								"localhost"
							],
							"port": "3000",
							"path": [
								"api",
								"organizations"
							]
						}
					},
					"response": []
				},
				{
					"name": "Update Organization",
					"request": {
						"method": "PATCH",
						"header": [
							{
								"key": "Authorization",
								"value": "Bearer YOUR_ACCESS_TOKEN"
							},
							{
								"key": "Content-Type",
								"value": "application/json"
							}
						],
						"body": {
							"mode": "raw",
							"raw": "{\n    \"name\": \"Updated Organization Name\",\n    \"email\": \"updated@org.com\",\n    \"phone_number\": \"9876543210\",\n    \"address\": \"Updated Address\"\n}",
							"options": {
								"raw": {
									"language": "json"
								}
							}
						},
						"url": {
							"raw": "http://localhost:3000/api/organizations/:organization_id",
							"protocol": "http",
							"host": [
								"localhost"
							],
							"port": "3000",
							"path": [
								"api",
								"organizations",
								":organization_id"
							],
							"variable": [
								{
									"key": "organization_id",
									"value": ""
								}
							]
						}
					},
					"response": []
				},
				{
					"name": "Delete Organization",
					"request": {
						"method": "DELETE",
						"header": [
							{
								"key": "Authorization",
								"value": "Bearer YOUR_ACCESS_TOKEN"
							}
						],
						"url": {
							"raw": "http://localhost:3000/api/organizations/:organization_id",
							"protocol": "http",
							"host": [
								"localhost"
							],
							"port": "3000",
							"path": [
								"api",
								"organizations",
								":organization_id"
							],
							"variable": [
								{
									"key": "organization_id",
									"value": ""
								}
							]
						}
					},
					"response": []
				}
			]
		},
		{
			"name": "Agencies",
			"item": [
				{
					"name": "Get All Agencies",
					"request": {
						"method": "GET",
						"header": [
							{
								"key": "Authorization",
								"value": "Bearer YOUR_JWT_TOKEN"
							}
						],
						"url": {
							"raw": "http://localhost:3000/api/agencies",
							"protocol": "http",
							"host": [
								"localhost"
							],
							"port": "3000",
							"path": [
								"api",
								"agencies"
							]
						}
					},
					"response": []
				},
				{
					"name": "Get a Specific Agency",
					"request": {
						"method": "GET",
						"header": [
							{
								"key": "Authorization",
								"value": "Bearer YOUR_JWT_TOKEN"
							}
						],
						"url": {
							"raw": "http://localhost:3000/api/agencies/AG1234567890",
							"protocol": "http",
							"host": [
								"localhost"
							],
							"port": "3000",
							"path": [
								"api",
								"agencies",
								"AG1234567890"
							]
						}
					},
					"response": []
				},
				{
					"name": "Create a New Agency",
					"request": {
						"method": "POST",
						"header": [
							{
								"key": "Authorization",
								"value": "Bearer YOUR_JWT_TOKEN"
							},
							{
								"key": "Content-Type",
								"value": "application/json"
							}
						],
						"body": {
							"mode": "raw",
							"raw": "{\n    \"name\": \"Example Agency\",\n    \"email\": \"agency@example.com\",\n    \"phone_number\": \"+1234567890\",\n    \"address\": \"123 Main St, City, Country\",\n    \"user_id\": \"USER_ID_HERE\"\n}",
							"options": {
								"raw": {
									"language": "json"
								}
							}
						},
						"url": {
							"raw": "http://localhost:3000/api/agencies",
							"protocol": "http",
							"host": [
								"localhost"
							],
							"port": "3000",
							"path": [
								"api",
								"agencies"
							]
						}
					},
					"response": []
				},
				{
					"name": "Update Agency",
					"request": {
						"method": "PATCH",
						"header": [
							{
								"key": "Authorization",
								"value": "Bearer YOUR_JWT_TOKEN"
							},
							{
								"key": "Content-Type",
								"value": "application/json"
							}
						],
						"body": {
							"mode": "raw",
							"raw": "{\n    \"name\": \"Updated Agency Name\",\n    \"email\": \"newemail@example.com\",\n    \"phone_number\": \"+1987654321\",\n    \"address\": \"456 New St, City, Country\"\n}",
							"options": {
								"raw": {
									"language": "json"
								}
							}
						},
						"url": {
							"raw": "http://localhost:3000/api/agencies/AG1234567890",
							"protocol": "http",
							"host": [
								"localhost"
							],
							"port": "3000",
							"path": [
								"api",
								"agencies",
								"AG1234567890"
							]
						}
					},
					"response": []
				},
				{
					"name": "Delete Agency",
					"request": {
						"method": "DELETE",
						"header": [
							{
								"key": "Authorization",
								"value": "Bearer YOUR_JWT_TOKEN"
							}
						],
						"url": {
							"raw": "http://localhost:3000/api/agencies/AG1234567890",
							"protocol": "http",
							"host": [
								"localhost"
							],
							"port": "3000",
							"path": [
								"api",
								"agencies",
								"AG1234567890"
							]
						}
					},
					"response": []
				}
			]
		},
		{
			"name": "Clients",
			"item": [
				{
					"name": "Get Clients",
					"request": {
						"method": "GET",
						"header": []
					},
					"response": []
				},
				{
					"name": "Get Specific Client",
					"request": {
						"method": "GET",
						"header": []
					},
					"response": []
				},
				{
					"name": "Create Client (Agency Only)",
					"request": {
						"method": "POST",
						"header": []
					},
					"response": []
				},
				{
					"name": "Update Client (Agency Only)",
					"request": {
						"method": "PATCH",
						"header": []
					},
					"response": []
				},
				{
					"name": "Link Client to Agency",
					"request": {
						"method": "POST",
						"header": []
					},
					"response": []
				},
				{
					"name": "Unlink Client to Agency",
					"request": {
						"method": "POST",
						"header": []
					},
					"response": []
				},
				{
					"name": "Delete Client (Agency Only)",
					"request": {
						"method": "DELETE",
						"header": []
					},
					"response": []
				}
			]
		},
		{
			"name": "AI Agent",
			"item": [
				{
					"name": "Get AI Agents",
					"request": {
						"method": "GET",
						"header": []
					},
					"response": []
				},
				{
					"name": "Get Specific AI Agent",
					"request": {
						"method": "GET",
						"header": []
					},
					"response": []
				},
				{
					"name": "Create AI Agent",
					"request": {
						"method": "POST",
						"header": []
					},
					"response": []
				},
				{
					"name": "Update AI Agent",
					"request": {
						"method": "PATCH",
						"header": []
					},
					"response": []
				},
				{
					"name": "Delete AI Agent",
					"request": {
						"method": "DELETE",
						"header": []
					},
					"response": []
				},
				{
					"name": "Get Agent Metrics",
					"request": {
						"method": "GET",
						"header": []
					},
					"response": []
				},
				{
					"name": "Get Most Active Agents",
					"request": {
						"method": "GET",
						"header": []
					},
					"response": []
				}
			]
		},
		{
			"name": "AI Configurations",
			"item": [
				{
					"name": "Get AI Configurations",
					"request": {
						"method": "GET",
						"header": []
					},
					"response": []
				},
				{
					"name": "Get Configuration by Client & Agent",
					"request": {
						"method": "GET",
						"header": []
					},
					"response": []
				},
				{
					"name": "Create AI Configuration",
					"request": {
						"method": "POST",
						"header": []
					},
					"response": []
				},
				{
					"name": "Update AI Configuration",
					"request": {
						"method": "PATCH",
						"header": []
					},
					"response": []
				},
				{
					"name": "Delete AI Configuration",
					"request": {
						"method": "DELETE",
						"header": []
					},
					"response": []
				},
				{
					"name": "Get Configurations by Type",
					"request": {
						"method": "GET",
						"header": []
					},
					"response": []
				},
				{
					"name": "Get Active Configurations",
					"request": {
						"method": "GET",
						"header": []
					},
					"response": []
				}
			]
		},
		{
			"name": "Call Logs",
			"item": [
				{
					"name": "Call Log",
					"item": [
						{
							"name": "Get Call Logs",
							"request": {
								"method": "GET",
								"header": []
							},
							"response": []
						},
						{
							"name": "Get Specific Call Log",
							"request": {
								"method": "GET",
								"header": []
							},
							"response": []
						},
						{
							"name": "Create Call Log",
							"request": {
								"method": "POST",
								"header": []
							},
							"response": []
						},
						{
							"name": "Update Call Log",
							"request": {
								"method": "PATCH",
								"header": []
							},
							"response": []
						},
						{
							"name": "Delete Call Log",
							"request": {
								"method": "DELETE",
								"header": []
							},
							"response": []
						},
						{
							"name": "Get Call Metrics",
							"request": {
								"method": "GET",
								"header": []
							},
							"response": []
						}
					]
				},
				{
					"name": "Metadata",
					"item": [
						{
							"name": "Get Call Metadata",
							"request": {
								"method": "GET",
								"header": []
							},
							"response": []
						},
						{
							"name": "Add/Update Metadata",
							"request": {
								"method": "POST",
								"header": []
							},
							"response": []
						},
						{
							"name": "Get Appointments",
							"request": {
								"method": "GET",
								"header": []
							},
							"response": []
						}
					]
				}
			]
		},
		{
			"name": "Modules",
			"item": [
				{
					"name": "Get Modules",
					"request": {
						"method": "GET",
						"header": []
					},
					"response": []
				},
				{
					"name": "Get Specific Module",
					"request": {
						"method": "GET",
						"header": []
					},
					"response": []
				},
				{
					"name": "Create Module",
					"request": {
						"method": "POST",
						"header": []
					},
					"response": []
				},
				{
					"name": "Update Module",
					"request": {
						"method": "PATCH",
						"header": []
					},
					"response": []
				},
				{
					"name": "Delete Module",
					"request": {
						"method": "DELETE",
						"header": []
					},
					"response": []
				}
			]
		},
		{
			"name": "User Permission",
			"item": [
				{
					"name": "Get All Permissions",
					"request": {
						"method": "GET",
						"header": []
					},
					"response": []
				},
				{
					"name": "Get User Permissions",
					"request": {
						"method": "GET",
						"header": []
					},
					"response": []
				},
				{
					"name": "Grant Permission",
					"request": {
						"method": "POST",
						"header": []
					},
					"response": []
				},
				{
					"name": "Update Permission",
					"request": {
						"method": "PATCH",
						"header": []
					},
					"response": []
				},
				{
					"name": "Revoke Permission",
					"request": {
						"method": "DELETE",
						"header": []
					},
					"response": []
				},
				{
					"name": "Check Permission",
					"request": {
						"method": "GET",
						"header": []
					},
					"response": []
				}
			]
		},
		{
			"name": "Billing Management",
			"item": [
				{
					"name": "Billing",
					"item": [
						{
							"name": "Get Credit Balance",
							"request": {
								"method": "GET",
								"header": []
							},
							"response": []
						},
						{
							"name": "Get All Transactions",
							"request": {
								"method": "GET",
								"header": []
							},
							"response": []
						},
						{
							"name": "Get User Transactions",
							"request": {
								"method": "GET",
								"header": []
							},
							"response": []
						},
						{
							"name": "Get Transaction Summary",
							"request": {
								"method": "GET",
								"header": []
							},
							"response": []
						},
						{
							"name": "Create Transaction",
							"request": {
								"method": "POST",
								"header": []
							},
							"response": []
						},
						{
							"name": "Update Transaction",
							"request": {
								"method": "PATCH",
								"header": []
							},
							"response": []
						},
						{
							"name": "Delete Transaction",
							"request": {
								"method": "DELETE",
								"header": []
							},
							"response": []
						}
					]
				},
				{
					"name": "Usage",
					"item": [
						{
							"name": "Get Usage Records",
							"request": {
								"method": "GET",
								"header": []
							},
							"response": []
						},
						{
							"name": "Get Usage Statistics",
							"request": {
								"method": "GET",
								"header": []
							},
							"response": []
						},
						{
							"name": "Get Usage Trends",
							"request": {
								"method": "GET",
								"header": []
							},
							"response": []
						},
						{
							"name": "Record Usage",
							"request": {
								"method": "POST",
								"header": []
							},
							"response": []
						},
						{
							"name": "Get High Usage Alerts",
							"request": {
								"method": "GET",
								"header": []
							},
							"response": []
						}
					]
				}
			]
		},
		{
			"name": "Client User Management",
			"item": [
				{
					"name": "Allowed Users",
					"item": [
						{
							"name": "Get Allowed Users",
							"request": {
								"method": "GET",
								"header": []
							},
							"response": []
						},
						{
							"name": "Get Specific Allowed User",
							"request": {
								"method": "GET",
								"header": []
							},
							"response": []
						},
						{
							"name": "Create Allowed User",
							"request": {
								"method": "POST",
								"header": []
							},
							"response": []
						},
						{
							"name": "Update Allowed User",
							"request": {
								"method": "PATCH",
								"header": []
							},
							"response": []
						},
						{
							"name": "Delete Allowed User",
							"request": {
								"method": "DELETE",
								"header": []
							},
							"response": []
						},
						{
							"name": "Renew Access",
							"request": {
								"method": "POST",
								"header": []
							},
							"response": []
						},
						{
							"name": "Track Time Usage",
							"request": {
								"method": "POST",
								"header": []
							},
							"response": []
						},
						{
							"name": "Get Usage Statistics",
							"request": {
								"method": "GET",
								"header": []
							},
							"response": []
						}
					]
				},
				{
					"name": "Customers",
					"item": [
						{
							"name": "Get Customers",
							"request": {
								"method": "GET",
								"header": []
							},
							"response": []
						},
						{
							"name": "Get Specific Customer",
							"request": {
								"method": "GET",
								"header": []
							},
							"response": []
						},
						{
							"name": "Create Customer",
							"request": {
								"method": "POST",
								"header": []
							},
							"response": []
						},
						{
							"name": "Update Customer",
							"request": {
								"method": "PATCH",
								"header": []
							},
							"response": []
						},
						{
							"name": "Get Customer Statistics",
							"request": {
								"method": "GET",
								"header": []
							},
							"response": []
						},
						{
							"name": "Find Customer by Phone",
							"request": {
								"method": "GET",
								"header": []
							},
							"response": []
						},
						{
							"name": "Get Follow-up List",
							"request": {
								"method": "GET",
								"header": []
							},
							"response": []
						}
					]
				},
				{
					"name": "Conversation History",
					"item": [
						{
							"name": "Get Customer History",
							"request": {
								"method": "GET",
								"header": []
							},
							"response": []
						},
						{
							"name": "Search Conversations",
							"request": {
								"method": "GET",
								"header": []
							},
							"response": []
						},
						{
							"name": "Get Conversation Statistics",
							"request": {
								"method": "GET",
								"header": []
							},
							"response": []
						},
						{
							"name": "Store Conversation",
							"request": {
								"method": "POST",
								"header": []
							},
							"response": []
						}
					]
				}
			]
		},
		{
			"name": "Subscription Plans",
			"item": [
				{
					"name": "Get Subscription Plans",
					"request": {
						"method": "GET",
						"header": []
					},
					"response": []
				},
				{
					"name": "Get Specific Plan",
					"request": {
						"method": "GET",
						"header": []
					},
					"response": []
				},
				{
					"name": "Create Subscription Plan",
					"request": {
						"method": "POST",
						"header": []
					},
					"response": []
				},
				{
					"name": "Update Subscription Plan",
					"request": {
						"method": "PATCH",
						"header": []
					},
					"response": []
				},
				{
					"name": "Delete Subscription Plan",
					"request": {
						"method": "DELETE",
						"header": []
					},
					"response": []
				},
				{
					"name": "Compare Plans",
					"request": {
						"method": "GET",
						"header": []
					},
					"response": []
				},
				{
					"name": "Get Recommended Plan",
					"request": {
						"method": "GET",
						"header": []
					},
					"response": []
				}
			]
		},
		{
			"name": "Communication Management",
			"item": [
				{
					"name": "Phone Numbers",
					"item": [
						{
							"name": "Get Phone Numbers",
							"request": {
								"method": "GET",
								"header": []
							},
							"response": []
						},
						{
							"name": "Get Specific Phone Number",
							"request": {
								"method": "GET",
								"header": []
							},
							"response": []
						},
						{
							"name": "Assign Phone Number",
							"request": {
								"method": "POST",
								"header": []
							},
							"response": []
						},
						{
							"name": "Update Phone Number",
							"request": {
								"method": "PATCH",
								"header": []
							},
							"response": []
						},
						{
							"name": "Release Phone Number",
							"request": {
								"method": "DELETE",
								"header": []
							},
							"response": []
						}
					]
				},
				{
					"name": "Call Recordings",
					"item": [
						{
							"name": "Get Recordings",
							"request": {
								"method": "GET",
								"header": []
							},
							"response": []
						},
						{
							"name": "Get Specific Recording",
							"request": {
								"method": "GET",
								"header": []
							},
							"response": []
						},
						{
							"name": "Upload Recording",
							"request": {
								"method": "POST",
								"header": []
							},
							"response": []
						},
						{
							"name": "Get Storage Statistics",
							"request": {
								"method": "GET",
								"header": []
							},
							"response": []
						}
					]
				}
			]
		},
		{
			"name": "Ticket Management",
			"item": [
				{
					"name": "Get Tickets",
					"request": {
						"method": "GET",
						"header": [
							{
								"key": "Authorization",
								"value": "Bearer YOUR_ACCESS_TOKEN"
							}
						],
						"url": {
							"raw": "http://localhost:3000/api/tickets",
							"protocol": "http",
							"host": [
								"localhost"
							],
							"port": "3000",
							"path": [
								"api",
								"tickets"
							]
						}
					},
					"response": []
				},
				{
					"name": "Get Specific Ticket",
					"request": {
						"method": "GET",
						"header": [
							{
								"key": "Authorization",
								"value": "Bearer YOUR_ACCESS_TOKEN"
							}
						],
						"url": {
							"raw": "http://localhost:3000/api/tickets/:ticket_id",
							"protocol": "http",
							"host": [
								"localhost"
							],
							"port": "3000",
							"path": [
								"api",
								"tickets",
								":ticket_id"
							],
							"variable": [
								{
									"key": "ticket_id",
									"value": ""
								}
							]
						}
					},
					"response": []
				},
				{
					"name": "Create Ticket",
					"request": {
						"method": "POST",
						"header": [
							{
								"key": "Authorization",
								"value": "Bearer YOUR_ACCESS_TOKEN"
							},
							{
								"key": "Content-Type",
								"value": "application/json"
							}
						],
						"body": {
							"mode": "raw",
							"raw": "{\n    \"agency_id\": \"AGENCY_ID\",\n    \"client_id\": \"CLIENT_ID\",\n    \"call_id\": \"CALL_ID\",\n    \"issue_description\": \"Detailed description of the issue\",\n    \"priority\": \"HIGH\",\n    \"category\": \"TECHNICAL\"\n}",
							"options": {
								"raw": {
									"language": "json"
								}
							}
						},
						"url": {
							"raw": "http://localhost:3000/api/tickets",
							"protocol": "http",
							"host": [
								"localhost"
							],
							"port": "3000",
							"path": [
								"api",
								"tickets"
							]
						}
					},
					"response": []
				},
				{
					"name": "Update Ticket Status",
					"request": {
						"method": "POST",
						"header": [
							{
								"key": "Authorization",
								"value": "Bearer YOUR_ACCESS_TOKEN"
							},
							{
								"key": "Content-Type",
								"value": "application/json"
							}
						],
						"body": {
							"mode": "raw",
							"raw": "{\n    \"status\": \"IN_PROGRESS\",\n    \"notes\": \"Working on resolution\"\n}",
							"options": {
								"raw": {
									"language": "json"
								}
							}
						},
						"url": {
							"raw": "http://localhost:3000/api/tickets/:ticket_id/status",
							"protocol": "http",
							"host": [
								"localhost"
							],
							"port": "3000",
							"path": [
								"api",
								"tickets",
								":ticket_id",
								"status"
							],
							"variable": [
								{
									"key": "ticket_id",
									"value": ""
								}
							]
						}
					},
					"response": []
				},
				{
					"name": "Add Resolution Note",
					"request": {
						"method": "POST",
						"header": [
							{
								"key": "Authorization",
								"value": "Bearer YOUR_ACCESS_TOKEN"
							},
							{
								"key": "Content-Type",
								"value": "application/json"
							}
						],
						"body": {
							"mode": "raw",
							"raw": "{\n    \"note\": \"Detailed resolution note\"\n}",
							"options": {
								"raw": {
									"language": "json"
								}
							}
						},
						"url": {
							"raw": "http://localhost:3000/api/tickets/:ticket_id/notes",
							"protocol": "http",
							"host": [
								"localhost"
							],
							"port": "3000",
							"path": [
								"api",
								"tickets",
								":ticket_id",
								"notes"
							],
							"variable": [
								{
									"key": "ticket_id",
									"value": ""
								}
							]
						}
					},
					"response": []
				},
				{
					"name": "Assign Ticket",
					"request": {
						"method": "POST",
						"header": [
							{
								"key": "Authorization",
								"value": "Bearer YOUR_ACCESS_TOKEN"
							},
							{
								"key": "Content-Type",
								"value": "application/json"
							}
						],
						"body": {
							"mode": "raw",
							"raw": "{\n    \"user_id\": \"USER_ID\"\n}",
							"options": {
								"raw": {
									"language": "json"
								}
							}
						},
						"url": {
							"raw": "http://localhost:3000/api/tickets/:ticket_id/assign",
							"protocol": "http",
							"host": [
								"localhost"
							],
							"port": "3000",
							"path": [
								"api",
								"tickets",
								":ticket_id",
								"assign"
							],
							"variable": [
								{
									"key": "ticket_id",
									"value": ""
								}
							]
						}
					},
					"response": []
				},
				{
					"name": "Get Ticket Statistics",
					"request": {
						"method": "GET",
						"header": [
							{
								"key": "Authorization",
								"value": "Bearer YOUR_ACCESS_TOKEN"
							}
						],
						"url": {
							"raw": "http://localhost:3000/api/tickets/stats",
							"protocol": "http",
							"host": [
								"localhost"
							],
							"port": "3000",
							"path": [
								"api",
								"tickets",
								"stats"
							]
						}
					},
					"response": []
				},
				{
					"name": "Get Overdue Tickets",
					"request": {
						"method": "GET",
						"header": [
							{
								"key": "Authorization",
								"value": "Bearer YOUR_ACCESS_TOKEN"
							}
						],
						"url": {
							"raw": "http://localhost:3000/api/tickets/overdue",
							"protocol": "http",
							"host": [
								"localhost"
							],
							"port": "3000",
							"path": [
								"api",
								"tickets",
								"overdue"
							]
						}
					},
					"response": []
				}
			]
		}
	]
}